<Circuit>
    <Name>Danube</Name>
    <Web>http</Web>
    <Cost>33.15</Cost>
    <JudgeDate>31-01-2020</JudgeDate>
    <NotificationDate>31-02-2020</NotificationDate>
    <Salons>
        <Salon>
            <Name>Romania</Name>
            <Country>Romania</Country>
            <Accreditations>
                <Accreditation type="PSA">2020-264</Accreditation>
                <Accreditation type="FIAPLevels">2020/248</Accreditation>
            </Accreditations>
            <AcceptedImages>
                <Image>Grasmere Rocks</Image>
                <Image>Dandelion Turbulance</Image>
            </AcceptedImages>
        </Salon>
        <Salon>
            <Name>Bulgaria</Name>
            <Country>Bulgaria</Country>
            <Accreditations>
                <Accreditation type="PSA">2020-264</Accreditation>
                <Accreditation type="FIAPLevels">2020/249</Accreditation>
            </Accreditations>
            <AcceptedImages>
                <Image>Common Toad On Rock</Image>
            </AcceptedImages>
        </Salon>
    </Salons>
</Circuit>